dataconf/__init__.py
dataconf/cli.py
dataconf/exceptions.py
dataconf/main.py
dataconf/py.typed
dataconf/utils.py
dataconf/version.py
pyproject.toml
dataconf-3.6.0.dist-info/LICENSE
dataconf-3.6.0.dist-info/METADATA
dataconf-3.6.0.dist-info/WHEEL
dataconf-3.6.0.dist-info/entry_points.txt
dataconf-3.6.0.dist-info/RECORD
