Metadata-Version: 2.1
Name: dataconf
Version: 3.6.0
Summary: Simple dataclasses configuration management for Python with hocon/json/yaml/properties/env-vars/dict support.
Home-page: https://github.com/zifeo/dataconf
License: MPL-2.0
Keywords: configuration,dataclasses,yaml,hocon,json,properties,cli,environment variables
Requires-Python: >=3.9,<4.0
Classifier: License :: OSI Approved
Classifier: Programming Language :: Python
Classifier: Programming Language :: Python :: 3
Classifier: Programming Language :: Python :: 3.9
Classifier: Programming Language :: Python :: 3.10
Classifier: Programming Language :: Python :: 3.11
Classifier: Programming Language :: Python :: 3.12
Classifier: Topic :: Software Development :: Libraries :: Python Modules
Requires-Dist: PyYAML (>=6.0.2,<7.0.0)
Requires-Dist: isodate (>=0.7.2,<0.8.0)
Requires-Dist: pyhocon (>=0.3.61,<0.4.0)
Requires-Dist: pyparsing (>=3.2.3,<4.0.0)
Requires-Dist: python-dateutil (>=2.9.0.post0,<3.0.0)
Project-URL: Repository, https://github.com/zifeo/dataconf
